anzu/__init__.py
anzu/__main__.py
anzu/logger/__init__.py
anzu/logger/logger.py
anzu/websocket/__init__.py
anzu/websocket/sockets.py
anzu/worker/__init__.py
anzu/worker/client.py
anzu/worker/constants.py
anzu/worker/exceptions.py
anzu/worker/utils.py
anzu-0.1.5.dist-info/METADATA
anzu-0.1.5.dist-info/WHEEL
anzu-0.1.5.dist-info/entry_points.txt
anzu-0.1.5.dist-info/licenses/LICENSE
anzu-0.1.5.dist-info/RECORD
