Metadata-Version: 2.4
Name: anzu
Version: 0.1.5
Summary: Anzu package for workers
Author-email: Your Name <your.email@example.com>
License: MIT
License-File: LICENSE
Keywords: django,queue,update
Classifier: License :: OSI Approved :: MIT License
Classifier: Operating System :: OS Independent
Classifier: Programming Language :: Python :: 3
Requires-Python: >=3.8
Requires-Dist: aiohttp>=3.7.3
Requires-Dist: python-socketio>=5.12.1
Requires-Dist: requests>=2.25.0
